[
    {
        "idMesa": 1,
        "estado": "Libre",
        "cliente": "Sin reserva"
    },
    {
        "idMesa": 2,
        "estado": "Libre",
        "cliente": "Sin reserva"
    },
    {
        "idMesa": 3,
        "estado": "Libre",
        "cliente": "Sin reserva"
    },
    {
        "idMesa": 4,
        "estado": "Libre",
        "cliente": "Sin reserva"
    },
    {
        "idMesa": 5,
        "estado": "Libre",
        "cliente": "Sin reserva"
    },
    {
        "idMesa": 6,
        "estado": "Libre",
        "cliente": "Sin reserva"
    }
]